nonebot_plugin_bf1marneserverlist/__init__.py
nonebot_plugin_bf1marneserverlist/config.py
nonebot_plugin_bf1marneserverlist-0.1.27.dist-info/METADATA
nonebot_plugin_bf1marneserverlist-0.1.27.dist-info/WHEEL
nonebot_plugin_bf1marneserverlist-0.1.27.dist-info/RECORD
