Metadata-Version: 2.1
Name: nonebot-plugin-bf1marneserverlist
Version: 0.1.27
Summary: nonebot-plugin-bf1marneserverlist
Author: safeluren
Requires-Python: >=3.8,<4.0
Classifier: Programming Language :: Python :: 3
Classifier: Programming Language :: Python :: 3.8
Classifier: Programming Language :: Python :: 3.9
Classifier: Programming Language :: Python :: 3.10
Classifier: Programming Language :: Python :: 3.11
Classifier: Programming Language :: Python :: 3.12
Requires-Dist: httpx (>=0.27.0,<0.28.0)
Requires-Dist: nonebot-adapter-onebot (>=2.4.0,<3.0.0)
Requires-Dist: nonebot-plugin-access-control-api (>=1.1.2,<2.0.0)
Requires-Dist: nonebot2 (>=2.2.1,<3.0.0)
Requires-Dist: nonebot_plugin_localstore (>=0.6.0,<0.7.0)
